paquete_hugo_fonseca/__init__.py
paquete_hugo_fonseca/estadisticos.py
paquete_hugo_fonseca-0.0.3.dist-info/LICENSE
paquete_hugo_fonseca-0.0.3.dist-info/METADATA
paquete_hugo_fonseca-0.0.3.dist-info/WHEEL
paquete_hugo_fonseca-0.0.3.dist-info/top_level.txt
paquete_hugo_fonseca-0.0.3.dist-info/RECORD
