Metadata-Version: 2.1
Name: paquete-hugo-fonseca
Version: 0.0.3
Summary: Paquete de estadisticos descriptivos para la clase de ML para economistas
Author-email: Hugo Fonseca <hugofonseca@usantotomas.edu.co>
License: MIT License        
Project-URL: Homepage, https://github.com/zack0712/paquete_hugo_fonseca
Project-URL: Bug Tracker, https://github.com/zack0712/paquete_hugo_fonseca/issues
Classifier: Programming Language :: Python :: 3
Classifier: License :: OSI Approved :: MIT License
Classifier: Operating System :: OS Independent
Requires-Python: >=3.7
License-File: LICENSE
